{
  "project_info": {
    "project_number": "717181494364",
    "firebase_url": "https://blood-donation-ac522.firebaseio.com",
    "project_id": "blood-donation-ac522",
    "storage_bucket": "blood-donation-ac522.appspot.com"
  },
  "client": [
    {
      "client_info": {
        "mobilesdk_app_id": "1:717181494364:android:25b6927b6c97c621d23299",
        "android_client_info": {
          "package_name": "com.example.blood"
        }
      },
      "oauth_client": [
        {
          "client_id": "717181494364-lek9u341ua3mjk3i6palnvibb9cnhgvu.apps.googleusercontent.com",
          "client_type": 3
        }
      ],
      "api_key": [
        {
          "current_key": "AIzaSyAjojvKLMN6NuGWmf4wIvfoOrqMq1SSn6A"
        }
      ],
      "services": {
        "appinvite_service": {
          "other_platform_oauth_client": [
            {
              "client_id": "717181494364-lek9u341ua3mjk3i6palnvibb9cnhgvu.apps.googleusercontent.com",
              "client_type": 3
            }
          ]
        }
      }
    }
  ],
  "configuration_version": "1"
}